imp/__init__.py
imp/py.typed
imp2importlib-0.1.1.dist-info/METADATA
imp2importlib-0.1.1.dist-info/WHEEL
imp2importlib-0.1.1.dist-info/entry_points.txt
imp2importlib-0.1.1.dist-info/RECORD
